{"dependencies":[{"name":"D:\\Javascript\\Emoji_guesser\\package.json","includedInParent":true,"mtime":1525557486000},{"name":"C:\\Users\\Loic\\AppData\\Local\\Yarn\\Data\\global\\node_modules\\parcel-bundler\\package.json","includedInParent":true,"mtime":1525392679000},{"name":"C:\\Users\\Loic\\AppData\\Local\\Yarn\\Data\\global\\node_modules\\parcel-bundler\\src\\.babelrc","includedInParent":true,"mtime":1518729375000}],"generated":{"js":"","map":{"mappings":[],"sources":{"C:\\Users\\Loic\\AppData\\Local\\Yarn\\Data\\global\\node_modules\\parcel-bundler\\src\\builtins\\_empty.js":""},"lineCount":null}},"hash":"2ae7ff4cf2fb65a454f0c6bfd8a495f4","cacheData":{"env":{}}}